connection_plugin
