Metadata-Version: 2.1
Name: airflow-connection-plugin
Version: 1.0.0
Summary: Templating for Airflow connections
Home-page: https://github.com/bakdata/connection_plugin
Author: bakdata
Author-email: opensource@bakdata.com
License: MIT
Platform: UNKNOWN
Classifier: License :: OSI Approved :: MIT License
Classifier: Programming Language :: Python :: 2
Classifier: Programming Language :: Python :: 2.7
Classifier: Programming Language :: Python :: 3
Classifier: Programming Language :: Python :: 3.5
Classifier: Programming Language :: Python :: 3.6
Requires-Python: >=2.7,!=3.0.*,!=3.1.*,!=3.2.*,!=3.3.*,!=3.4.*
